pelican_provisioner
